{
  "id": "c62df3f5-b75a-4197-b941-d9c367858b54",
  "title": "2025-11-26",
  "session_date": "2025-11-26",
  "mode": "random_topic",
  "topic": "Rain streaked down the bay window, blurring the city into a watercolor smear, but inside, the heavy velvet drapes kept the chill at bay. The scent of star anise and old parchment mingled in the air, a familiar comfort as Elara traced a finger along the spines of her bound grimoires. She hadn't expected the faint luminescence of the arcane sigil on the antique map spread across her oak desk, not after all these years.",
  "content": "她恍惚地走进这间她遗忘已久的小屋，走进植物的馥郁香气里。被雨水稀释的血顺着外套滴落在厚厚的织物地毯上，但她没有关心被打湿的地毯。她只是看着陈旧地图上符号的光盈满了房间。\n在童年之后，她还是再次来到了这里。\n她脱掉身上的外套，从书架上抽下那本法术书——或者说，它自己从书架上跳了出来，跃进她手中。这本书……这个地方，是属于她的。或者说，她属于这里，因此无论如何她都会回到这里。如果她自己拒绝这条路，命运总能让她不得不再次发现自己重新站在这里。所以她不会再拒绝它。也不会拒绝自己将因不得不选择它所付出的代价。\n她清晰地知道自己需要什么。不是清洁法术，不是更困难一点的让人遗忘的咒语，而是能够与这个世界上横行的种种不幸、荒诞不经又不请自来的意外抗衡的力量，能够彻底驱逐与杀死那个易皮鬼的能力。拒绝受命运摆布的能力。\n她的手指顺着目录页缓慢地滑下去，停在了最后一行字上。书籍的最后几页。她试着翻开对应的页码，但书的反应很激烈。她尝试了几次，那一页就像是装帧有问题一样总被前一页或者后一页盖住，最后整本书干脆地从她手里滑出去，砸在她的脚趾上。她看着合好自己躺在地上的书，深呼吸了一下，对它说：“我一定要使用那个法术。即使把那一页从你身上裁下来，我也一定要看到它。”\n书没有回应她的威胁，只是一动不动地躺在地上，像是在和她无声地对峙。人书对峙了片刻，她慢慢抬起手，盖住了自己的脸。\n几分钟的寂静后，她从地上捡起书，轻轻拍了拍书在地毯上沾到的灰尘。\n“……抱歉，我太心急了。”她低着头对这本不会回答的书说，“尽管我已经只有自己了……我依然不能接受失去任何东西了。不论是什么原因都不行。所以我必须要读到那一页。”\n然后她再度翻开书。这次，书页抖动了一下，最终还是没有遮住她需要的那页法术。",
  "start_time": "2025-11-26T22:28:01.898690",
  "end_time": "2025-11-26T22:57:37.207404",
  "duration_seconds": 1775,
  "char_count": 736,
  "word_count": 653
}